{"filename": "Shiflina Nilofar P_data_analyst_resume.docx", "extracted_text": "Shiflina Nilofar P\n+91 9342003015 |  |  | Ayapakkam, Chennai | \nResults-driven and enthusiastic Data Engineering fresher with hands-on experience in Python, SQL, and data analysis. Eager to contribute to building efficient data pipelines and infrastructure as a Big Data Engineer. Seeking to grow within a dynamic tech environment and help organizations harness the power of big data for actionable insights.\nEducation\nBachelor Of Computer Applications (BCA)\nQueen Mary’s College, Chennai | 08/2022 – 05/2025 | CGPA : 7.4\nHigher Secondary\nGirls Government Higher Secondary School, Ayapakkam | 06/2021 – 05/2022 | Percentage : 84%\nSkills\nLanguages & Tools: Python (Intermediate), PL/SQL, MySQL, NumPy, Pandas, Excel, Tableau\nData Engineering Tools: ETL Concepts, Data Modeling, Data Cleaning\nSoft Skills: Communication, Problem-Solving, Teamwork, Project Management\n\nProjects\nInventory Management System\nBuilt using Python, Pandas, and MySQL.\nAutomated inventory tracking, restocking alerts, and reporting.\nDesigned interactive dashboards for stock visualization.\nCertifications\nPython Programming – GUVI\nSQL Gold Badge – HackerRank\nAchievements\n1st Runner-Up – Web Designing Competition (The New College, 2025)\n1st Runner-Up – Coding Challenge (Python) (MCC College, 2025)\nWinners – Project Expo with Team Project (Measi Institute of Information Technology, 2025)\nSimulation\nAccenture North America Data Analytics and Visualization Job Simulation on Forage - June 2024\nCompleted a simulation focused on advising a hypothetical social media client as a Data Analyst at Accenture\nCleaned, modelled and analyzed 7 datasets to uncover insights into content trends to inform strategic decisions\nPrepared a PowerPoint deck and video presentation to communicate key insights for the client and internal stakeholders\n", "processed_data": {"cleaned_text": "shiflina nilofar p\n91 9342003015 | | | ayapakkam, chennai |\nresults-driven and enthusiastic data engineering fresher with hands-on experience in python, sql, and data analysis. eager to contribute to building efficient data pipelines and infrastructure as a big data engineer. seeking to grow within a dynamic tech environment and help organizations harness the power of big data for actionable insights.\neducation\nbachelor of computer applications (bca)\nqueen mary s college, chennai | 08 2022   05 2025 | cgpa : 7.4\nhigher secondary\ngirls government higher secondary school, ayapakkam | 06 2021   05 2022 | percentage : 84\nskills\nlanguages   tools: python (intermediate), pl sql, mysql, numpy, pandas, excel, tableau\ndata engineering tools: etl concepts, data modeling, data cleaning\nsoft skills: communication, problem-solving, teamwork, project management\nprojects\ninventory management system\nbuilt using python, pandas, and mysql.\nautomated inventory tracking, restocking alerts, and reporting.\ndesigned interactive dashboards for stock visualization.\ncertifications\npython programming   guvi\nsql gold badge   hackerrank\nachievements\n1st runner-up   web designing competition (the new college, 2025)\n1st runner-up   coding challenge (python) (mcc college, 2025)\nwinners   project expo with team project (measi institute of information technology, 2025)\nsimulation\naccenture north america data analytics and visualization job simulation on forage - june 2024\ncompleted a simulation focused on advising a hypothetical social media client as a data analyst at accenture\ncleaned, modelled and analyzed 7 datasets to uncover insights into content trends to inform strategic decisions\nprepared a powerpoint deck and video presentation to communicate key insights for the client and internal stakeholders", "tokens": ["shiflina", "nilofar", "91", "9342003015", "ayapakkam", "chennai", "result", "drive", "enthusiastic", "datum", "engineering", "fresher", "hand", "experience", "python", "sql", "datum", "analysis", "eager", "contribute", "build", "efficient", "datum", "pipeline", "infrastructure", "big", "data", "engineer", "seek", "grow", "dynamic", "tech", "environment", "help", "organization", "harness", "power", "big", "datum", "actionable", "insight", "education", "bachelor", "computer", "application", "bca", "queen", "mary", "college", "chennai", "08", "2022", "05", "2025", "cgpa", "7.4", "high", "secondary", "girl", "government", "high", "secondary", "school", "ayapakkam", "06", "2021", "05", "2022", "percentage", "84", "skill", "language", "tool", "python", "intermediate", "pl", "sql", "mysql", "numpy", "panda", "excel", "tableau", "datum", "engineering", "tool", "etl", "concept", "datum", "modeling", "datum", "clean", "soft", "skill", "communication", "problem", "solving", "teamwork", "project", "management", "project", "inventory", "management", "system", "build", "python", "panda", "mysql", "automate", "inventory", "tracking", "restock", "alert", "report", "design", "interactive", "dashboard", "stock", "visualization", "certification", "python", "programming", "guvi", "sql", "gold", "badge", "hackerrank", "achievement", "1st", "runner", "web", "designing", "competition", "new", "college", "2025", "1st", "runner", "code", "challenge", "python", "mcc", "college", "2025", "winner", "project", "expo", "team", "project", "measi", "institute", "information", "technology", "2025", "simulation", "accenture", "north", "america", "data", "analytic", "visualization", "job", "simulation", "forage", "june", "2024", "complete", "simulation", "focus", "advise", "hypothetical", "social", "medium", "client", "data", "analyst", "accenture", "clean", "model", "analyze", "dataset", "uncover", "insight", "content", "trend", "inform", "strategic", "decision", "prepare", "powerpoint", "deck", "video", "presentation", "communicate", "key", "insight", "client", "internal", "stakeholder"], "entities": {"PERSON": ["mary s college"], "ORG": ["cgpa", "pandas", "measi institute of information technology"], "GPE": ["shiflina"], "DATE": ["08 2022", "05 2025", "06 2021", "05 2022", "2025", "june 2024"], "MONEY": [], "PERCENT": [], "TIME": [], "EVENT": [], "FAC": [], "LANGUAGE": [], "LAW": [], "LOC": ["north america"], "NORP": [], "PRODUCT": [], "WORK_OF_ART": []}, "skills": ["data analysis", "datasets", "excel", "mysql", "numpy", "pandas", "pl/sql", "python", "sql", "tableau"], "locations": ["America", "Chennai", "north america", "shiflina"], "certifications": [{"name": "python programming", "issuer": "GUVI", "date": ""}, {"name": "sql gold badge", "issuer": "Hackerrank", "date": ""}], "education": [{"degree": "bachelor", "institution": "queen mary s college, chennai | 08 2022   05 2025 | cgpa : 7.4", "dates": "", "grade": ""}, {"degree": "", "institution": "queen mary s college, chennai | 08 2022   05 2025 | cgpa : 7.4", "dates": "", "grade": ""}, {"degree": "me", "institution": "girls government higher secondary school, ayapakkam | 06 2021   05 2022 | percentage : 84", "dates": "", "grade": ""}, {"institution": "queen mary's college", "degree": "", "dates": "", "grade": ""}, {"institution": "the new college", "degree": "", "dates": "", "grade": ""}, {"institution": "mcc college", "degree": "", "dates": "", "grade": ""}], "experience_details": {"companies": [], "positions": ["analyst"], "duration": ["june"], "technologies": []}, "projects": [{"name": "inventory management system\nbuilt", "description": "Keywords: inventory management, dashboard, data pipeline, etl", "technologies": ["python", "pandas", "mysql", "sql"]}, {"name": "automated inventory tracking, restocking alerts, and reporting", "description": "automated inventory tracking, restocking alerts, and reporting", "technologies": ["data analysis", "datasets", "excel", "mysql", "numpy", "pandas"]}, {"name": "designed interactive dashboards for stock visualization", "description": "designed interactive dashboards for stock visualization", "technologies": ["data analysis", "datasets", "excel", "mysql", "numpy", "pandas"]}], "achievements": ["1st runner-up   web designing competition (the new college, 2025", "1st runner-up   coding challenge (python) (mcc college, 2025", "winners   project expo with team project (measi institute of information technology"], "field_of_interest": ["web crasher"], "text_length": 1802, "token_count": 198, "experience": [{"company": "", "position": "analyst", "dates": "june", "description": ""}], "fields_of_interest": ["web crasher"], "location": "America", "name": "mary s college", "phone": "+91 9342003015"}, "session_data": {"filename": "Shiflina Nilofar P_data_analyst_resume.docx", "extracted_text": "Shiflina Nilofar P\n+91 9342003015 |  |  | Ayapakkam, Chennai | \nResults-driven and enthusiastic Data Engineering fresher with hands-on experience in Python, SQL, and data analysis. Eager to contribute to building efficient data pipelines and infrastructure as a Big Data Engineer. Seeking to grow within a dynamic tech environment and help organizations harness the power of big data for actionable insights.\nEducation\nBachelor Of Computer Applications (BCA)\nQueen Mary’s College, Chennai | 08/2022 – 05/2025 | CGPA : 7.4\nHigher Secondary\nGirls Government Higher Secondary School, Ayapakkam | 06/2021 – 05/2022 | Percentage : 84%\nSkills\nLanguages & Tools: Python (Intermediate), PL/SQL, MySQL, NumPy, Pandas, Excel, Tableau\nData Engineering Tools: ETL Concepts, Data Modeling, Data Cleaning\nSoft Skills: Communication, Problem-Solving, Teamwork, Project Management\n\nProjects\nInventory Management System\nBuilt using Python, Pandas, and MySQL.\nAutomated inventory tracking, restocking alerts, and reporting.\nDesigned interactive dashboards for stock visualization.\nCertifications\nPython Programming – GUVI\nSQL Gold Badge – HackerRank\nAchievements\n1st Runner-Up – Web Designing Competition (The New College, 2025)\n1st Runner-Up – Coding Challenge (Python) (MCC College, 2025)\nWinners – Project Expo with Team Project (Measi Institute of Information Technology, 2025)\nSimulation\nAccenture North America Data Analytics and Visualization Job Simulation on Forage - June 2024\nCompleted a simulation focused on advising a hypothetical social media client as a Data Analyst at Accenture\nCleaned, modelled and analyzed 7 datasets to uncover insights into content trends to inform strategic decisions\nPrepared a PowerPoint deck and video presentation to communicate key insights for the client and internal stakeholders\n", "processed_data": {"cleaned_text": "shiflina nilofar p\n91 9342003015 | | | ayapakkam, chennai |\nresults-driven and enthusiastic data engineering fresher with hands-on experience in python, sql, and data analysis. eager to contribute to building efficient data pipelines and infrastructure as a big data engineer. seeking to grow within a dynamic tech environment and help organizations harness the power of big data for actionable insights.\neducation\nbachelor of computer applications (bca)\nqueen mary s college, chennai | 08 2022   05 2025 | cgpa : 7.4\nhigher secondary\ngirls government higher secondary school, ayapakkam | 06 2021   05 2022 | percentage : 84\nskills\nlanguages   tools: python (intermediate), pl sql, mysql, numpy, pandas, excel, tableau\ndata engineering tools: etl concepts, data modeling, data cleaning\nsoft skills: communication, problem-solving, teamwork, project management\nprojects\ninventory management system\nbuilt using python, pandas, and mysql.\nautomated inventory tracking, restocking alerts, and reporting.\ndesigned interactive dashboards for stock visualization.\ncertifications\npython programming   guvi\nsql gold badge   hackerrank\nachievements\n1st runner-up   web designing competition (the new college, 2025)\n1st runner-up   coding challenge (python) (mcc college, 2025)\nwinners   project expo with team project (measi institute of information technology, 2025)\nsimulation\naccenture north america data analytics and visualization job simulation on forage - june 2024\ncompleted a simulation focused on advising a hypothetical social media client as a data analyst at accenture\ncleaned, modelled and analyzed 7 datasets to uncover insights into content trends to inform strategic decisions\nprepared a powerpoint deck and video presentation to communicate key insights for the client and internal stakeholders", "tokens": ["shiflina", "nilofar", "91", "9342003015", "ayapakkam", "chennai", "result", "drive", "enthusiastic", "datum", "engineering", "fresher", "hand", "experience", "python", "sql", "datum", "analysis", "eager", "contribute", "build", "efficient", "datum", "pipeline", "infrastructure", "big", "data", "engineer", "seek", "grow", "dynamic", "tech", "environment", "help", "organization", "harness", "power", "big", "datum", "actionable", "insight", "education", "bachelor", "computer", "application", "bca", "queen", "mary", "college", "chennai", "08", "2022", "05", "2025", "cgpa", "7.4", "high", "secondary", "girl", "government", "high", "secondary", "school", "ayapakkam", "06", "2021", "05", "2022", "percentage", "84", "skill", "language", "tool", "python", "intermediate", "pl", "sql", "mysql", "numpy", "panda", "excel", "tableau", "datum", "engineering", "tool", "etl", "concept", "datum", "modeling", "datum", "clean", "soft", "skill", "communication", "problem", "solving", "teamwork", "project", "management", "project", "inventory", "management", "system", "build", "python", "panda", "mysql", "automate", "inventory", "tracking", "restock", "alert", "report", "design", "interactive", "dashboard", "stock", "visualization", "certification", "python", "programming", "guvi", "sql", "gold", "badge", "hackerrank", "achievement", "1st", "runner", "web", "designing", "competition", "new", "college", "2025", "1st", "runner", "code", "challenge", "python", "mcc", "college", "2025", "winner", "project", "expo", "team", "project", "measi", "institute", "information", "technology", "2025", "simulation", "accenture", "north", "america", "data", "analytic", "visualization", "job", "simulation", "forage", "june", "2024", "complete", "simulation", "focus", "advise", "hypothetical", "social", "medium", "client", "data", "analyst", "accenture", "clean", "model", "analyze", "dataset", "uncover", "insight", "content", "trend", "inform", "strategic", "decision", "prepare", "powerpoint", "deck", "video", "presentation", "communicate", "key", "insight", "client", "internal", "stakeholder"], "entities": {"PERSON": ["mary s college"], "ORG": ["cgpa", "pandas", "measi institute of information technology"], "GPE": ["shiflina"], "DATE": ["08 2022", "05 2025", "06 2021", "05 2022", "2025", "june 2024"], "MONEY": [], "PERCENT": [], "TIME": [], "EVENT": [], "FAC": [], "LANGUAGE": [], "LAW": [], "LOC": ["north america"], "NORP": [], "PRODUCT": [], "WORK_OF_ART": []}, "skills": ["data analysis", "datasets", "excel", "mysql", "numpy", "pandas", "pl/sql", "python", "sql", "tableau"], "locations": ["America", "Chennai", "north america", "shiflina"], "certifications": [{"name": "python programming", "issuer": "GUVI", "date": ""}, {"name": "sql gold badge", "issuer": "Hackerrank", "date": ""}], "education": [{"degree": "bachelor", "institution": "queen mary s college, chennai | 08 2022   05 2025 | cgpa : 7.4", "dates": "", "grade": ""}, {"degree": "", "institution": "queen mary s college, chennai | 08 2022   05 2025 | cgpa : 7.4", "dates": "", "grade": ""}, {"degree": "me", "institution": "girls government higher secondary school, ayapakkam | 06 2021   05 2022 | percentage : 84", "dates": "", "grade": ""}, {"institution": "queen mary's college", "degree": "", "dates": "", "grade": ""}, {"institution": "the new college", "degree": "", "dates": "", "grade": ""}, {"institution": "mcc college", "degree": "", "dates": "", "grade": ""}], "experience_details": {"companies": [], "positions": ["analyst"], "duration": ["june"], "technologies": []}, "projects": [{"name": "inventory management system\nbuilt", "description": "Keywords: inventory management, dashboard, data pipeline, etl", "technologies": ["python", "pandas", "mysql", "sql"]}, {"name": "automated inventory tracking, restocking alerts, and reporting", "description": "automated inventory tracking, restocking alerts, and reporting", "technologies": ["data analysis", "datasets", "excel", "mysql", "numpy", "pandas"]}, {"name": "designed interactive dashboards for stock visualization", "description": "designed interactive dashboards for stock visualization", "technologies": ["data analysis", "datasets", "excel", "mysql", "numpy", "pandas"]}], "achievements": ["1st runner-up   web designing competition (the new college, 2025", "1st runner-up   coding challenge (python) (mcc college, 2025", "winners   project expo with team project (measi institute of information technology"], "field_of_interest": ["web designing"], "text_length": 1802, "token_count": 198, "experience": [{"company": "", "position": "analyst", "dates": "june", "description": ""}], "fields_of_interest": ["web designing"], "location": "America", "name": "mary s college", "phone": "+91 9342003015"}, "session_data": {"filename": "Shiflina Nilofar P_data_analyst_resume.docx", "extracted_text": "Shiflina Nilofar P\n+91 9342003015 |  |  | Ayapakkam, Chennai | \nResults-driven and enthusiastic Data Engineering fresher with hands-on experience in Python, SQL, and data analysis. Eager to contribute to building efficient data pipelines and infrastructure as a Big Data Engineer. Seeking to grow within a dynamic tech environment and help organizations harness the power of big data for actionable insights.\nEducation\nBachelor Of Computer Applications (BCA)\nQueen Mary’s College, Chennai | 08/2022 – 05/2025 | CGPA : 7.4\nHigher Secondary\nGirls Government Higher Secondary School, Ayapakkam | 06/2021 – 05/2022 | Percentage : 84%\nSkills\nLanguages & Tools: Python (Intermediate), PL/SQL, MySQL, NumPy, Pandas, Excel, Tableau\nData Engineering Tools: ETL Concepts, Data Modeling, Data Cleaning\nSoft Skills: Communication, Problem-Solving, Teamwork, Project Management\n\nProjects\nInventory Management System\nBuilt using Python, Pandas, and MySQL.\nAutomated inventory tracking, restocking alerts, and reporting.\nDesigned interactive dashboards for stock visualization.\nCertifications\nPython Programming – GUVI\nSQL Gold Badge – HackerRank\nAchievements\n1st Runner-Up – Web Designing Competition (The New College, 2025)\n1st Runner-Up – Coding Challenge (Python) (MCC College, 2025)\nWinners – Project Expo with Team Project (Measi Institute of Information Technology, 2025)\nSimulation\nAccenture North America Data Analytics and Visualization Job Simulation on Forage - June 2024\nCompleted a simulation focused on advising a hypothetical social media client as a Data Analyst at Accenture\nCleaned, modelled and analyzed 7 datasets to uncover insights into content trends to inform strategic decisions\nPrepared a PowerPoint deck and video presentation to communicate key insights for the client and internal stakeholders\n", "processed_data": {"cleaned_text": "shiflina nilofar p\n91 9342003015 | | | ayapakkam, chennai |\nresults-driven and enthusiastic data engineering fresher with hands-on experience in python, sql, and data analysis. eager to contribute to building efficient data pipelines and infrastructure as a big data engineer. seeking to grow within a dynamic tech environment and help organizations harness the power of big data for actionable insights.\neducation\nbachelor of computer applications (bca)\nqueen mary s college, chennai | 08 2022   05 2025 | cgpa : 7.4\nhigher secondary\ngirls government higher secondary school, ayapakkam | 06 2021   05 2022 | percentage : 84\nskills\nlanguages   tools: python (intermediate), pl sql, mysql, numpy, pandas, excel, tableau\ndata engineering tools: etl concepts, data modeling, data cleaning\nsoft skills: communication, problem-solving, teamwork, project management\nprojects\ninventory management system\nbuilt using python, pandas, and mysql.\nautomated inventory tracking, restocking alerts, and reporting.\ndesigned interactive dashboards for stock visualization.\ncertifications\npython programming   guvi\nsql gold badge   hackerrank\nachievements\n1st runner-up   web designing competition (the new college, 2025)\n1st runner-up   coding challenge (python) (mcc college, 2025)\nwinners   project expo with team project (measi institute of information technology, 2025)\nsimulation\naccenture north america data analytics and visualization job simulation on forage - june 2024\ncompleted a simulation focused on advising a hypothetical social media client as a data analyst at accenture\ncleaned, modelled and analyzed 7 datasets to uncover insights into content trends to inform strategic decisions\nprepared a powerpoint deck and video presentation to communicate key insights for the client and internal stakeholders", "tokens": ["shiflina", "nilofar", "91", "9342003015", "ayapakkam", "chennai", "result", "drive", "enthusiastic", "datum", "engineering", "fresher", "hand", "experience", "python", "sql", "datum", "analysis", "eager", "contribute", "build", "efficient", "datum", "pipeline", "infrastructure", "big", "data", "engineer", "seek", "grow", "dynamic", "tech", "environment", "help", "organization", "harness", "power", "big", "datum", "actionable", "insight", "education", "bachelor", "computer", "application", "bca", "queen", "mary", "college", "chennai", "08", "2022", "05", "2025", "cgpa", "7.4", "high", "secondary", "girl", "government", "high", "secondary", "school", "ayapakkam", "06", "2021", "05", "2022", "percentage", "84", "skill", "language", "tool", "python", "intermediate", "pl", "sql", "mysql", "numpy", "panda", "excel", "tableau", "datum", "engineering", "tool", "etl", "concept", "datum", "modeling", "datum", "clean", "soft", "skill", "communication", "problem", "solving", "teamwork", "project", "management", "project", "inventory", "management", "system", "build", "python", "panda", "mysql", "automate", "inventory", "tracking", "restock", "alert", "report", "design", "interactive", "dashboard", "stock", "visualization", "certification", "python", "programming", "guvi", "sql", "gold", "badge", "hackerrank", "achievement", "1st", "runner", "web", "designing", "competition", "new", "college", "2025", "1st", "runner", "code", "challenge", "python", "mcc", "college", "2025", "winner", "project", "expo", "team", "project", "measi", "institute", "information", "technology", "2025", "simulation", "accenture", "north", "america", "data", "analytic", "visualization", "job", "simulation", "forage", "june", "2024", "complete", "simulation", "focus", "advise", "hypothetical", "social", "medium", "client", "data", "analyst", "accenture", "clean", "model", "analyze", "dataset", "uncover", "insight", "content", "trend", "inform", "strategic", "decision", "prepare", "powerpoint", "deck", "video", "presentation", "communicate", "key", "insight", "client", "internal", "stakeholder"], "entities": {"PERSON": ["mary s college"], "ORG": ["cgpa", "pandas", "measi institute of information technology"], "GPE": ["shiflina"], "DATE": ["08 2022", "05 2025", "06 2021", "05 2022", "2025", "june 2024"], "MONEY": [], "PERCENT": [], "TIME": [], "EVENT": [], "FAC": [], "LANGUAGE": [], "LAW": [], "LOC": ["north america"], "NORP": [], "PRODUCT": [], "WORK_OF_ART": []}, "skills": ["data analysis", "datasets", "excel", "mysql", "numpy", "pandas", "pl/sql", "python", "sql", "tableau"], "locations": ["America", "Chennai", "north america", "shiflina"], "certifications": [{"name": "python programming", "issuer": "GUVI", "date": ""}, {"name": "sql gold badge", "issuer": "Hackerrank", "date": ""}], "education": [{"degree": "bachelor", "institution": "queen mary s college, chennai | 08 2022   05 2025 | cgpa : 7.4", "dates": "", "grade": ""}, {"degree": "", "institution": "queen mary s college, chennai | 08 2022   05 2025 | cgpa : 7.4", "dates": "", "grade": ""}, {"degree": "me", "institution": "girls government higher secondary school, ayapakkam | 06 2021   05 2022 | percentage : 84", "dates": "", "grade": ""}, {"institution": "queen mary's college", "degree": "", "dates": "", "grade": ""}, {"institution": "the new college", "degree": "", "dates": "", "grade": ""}, {"institution": "mcc college", "degree": "", "dates": "", "grade": ""}], "experience_details": {"companies": [], "positions": ["analyst"], "duration": ["june"], "technologies": []}, "projects": [{"name": "inventory management system\nbuilt", "description": "Keywords: inventory management, dashboard, data pipeline, etl", "technologies": ["python", "pandas", "mysql", "sql"]}, {"name": "automated inventory tracking, restocking alerts, and reporting", "description": "automated inventory tracking, restocking alerts, and reporting", "technologies": ["data analysis", "datasets", "excel", "mysql", "numpy", "pandas"]}, {"name": "designed interactive dashboards for stock visualization", "description": "designed interactive dashboards for stock visualization", "technologies": ["data analysis", "datasets", "excel", "mysql", "numpy", "pandas"]}], "achievements": ["1st runner-up   web designing competition (the new college, 2025", "1st runner-up   coding challenge (python) (mcc college, 2025", "winners   project expo with team project (measi institute of information technology"], "field_of_interest": [], "text_length": 1802, "token_count": 198, "experience": [{"company": "", "position": "analyst", "dates": "june", "description": ""}], "fields_of_interest": [], "location": "America", "name": "mary s college", "phone": "+91 9342003015"}, "hints": {"headings": [], "sections": [], "bold_lines": ["Shiflina Nilofar P", "Bachelor Of Computer Applications (BCA)\nQueen Mary’s College, Chennai | 08/2022 – 05/2025 | CGPA : 7.4", "Higher Secondary\nGirls Government Higher Secondary School, Ayapakkam | 06/2021 – 05/2022 | Percentage : 84%", "Inventory Management System", "Accenture North America Data Analytics and Visualization Job Simulation on Forage - June 2024"], "education_candidates": ["Bachelor Of Computer Applications (BCA)\nQueen Mary’s College, Chennai | 08/2022 – 05/2025 | CGPA : 7.4", "1st Runner-Up – Web Designing Competition (The New College, 2025)", "1st Runner-Up – Coding Challenge (Python) (MCC College, 2025)"]}}, "user_edited": false}, "user_edited": false}